dbt/__init__.py
dbt/adapters/hologres/__init__.py
dbt/adapters/hologres/__version__.py
dbt/adapters/hologres/date.py
dbt/adapters/hologres/impl.py
dbt/adapters/hologres/relation.py
dbt/include/hologres/__init__.py
dbt/include/hologres/dbt_project.yml
dbt/include/hologres/macros.yml
dbt/include/hologres/profile_template.yml
dbt/include/hologres/sample_profiles.yml
dbt/include/hologres/macros/adapters.sql
dbt/include/hologres/macros/catalog.sql
dbt/include/hologres/macros/relations.sql
dbt/include/hologres/macros/timestamps.sql
dbt/include/hologres/macros/materializations/incremental.sql
dbt/include/hologres/macros/materializations/incremental_strategies.sql
dbt/include/hologres/macros/materializations/seed.sql
dbt/include/hologres/macros/materializations/snapshot_merge.sql
dbt/include/hologres/macros/materializations/table.sql
dbt/include/hologres/macros/materializations/view.sql
dbt/include/hologres/macros/relations/materialized_view/alter.sql
dbt/include/hologres/macros/relations/materialized_view/create.sql
dbt/include/hologres/macros/relations/materialized_view/describe.sql
dbt/include/hologres/macros/relations/materialized_view/drop.sql
dbt/include/hologres/macros/relations/materialized_view/refresh.sql
dbt/include/hologres/macros/relations/materialized_view/rename.sql
dbt/include/hologres/macros/relations/table/drop.sql
dbt/include/hologres/macros/relations/table/rename.sql
dbt/include/hologres/macros/relations/table/replace.sql
dbt/include/hologres/macros/relations/view/drop.sql
dbt/include/hologres/macros/relations/view/rename.sql
dbt/include/hologres/macros/relations/view/replace.sql
dbt/include/hologres/macros/utils/any_value.sql
dbt/include/hologres/macros/utils/columns_spec_ddl.sql
dbt/include/hologres/macros/utils/dateadd.sql
dbt/include/hologres/macros/utils/datediff.sql
dbt/include/hologres/macros/utils/dateutil.sql
dbt/include/hologres/macros/utils/last_day.sql
dbt/include/hologres/macros/utils/listagg.sql
dbt_hologres-1.9.1.dist-info/METADATA
dbt_hologres-1.9.1.dist-info/WHEEL
dbt_hologres-1.9.1.dist-info/licenses/LICENSE
dbt_hologres-1.9.1.dist-info/RECORD
